airalo/__init__.py
airalo/airalo.py
airalo/config.py
airalo/constants/__init__.py
airalo/constants/api_constants.py
airalo/constants/sdk_constants.py
airalo/exceptions/__init__.py
airalo/exceptions/airalo_exception.py
airalo/helpers/__init__.py
airalo/helpers/cached.py
airalo/helpers/cloud_sim_share_validator.py
airalo/helpers/crypt.py
airalo/helpers/date_helper.py
airalo/helpers/signature.py
airalo/resources/__init__.py
airalo/resources/http_resource.py
airalo/resources/multi_http_resource.py
airalo/services/__init__.py
airalo/services/compatibility_devices_service.py
airalo/services/exchange_rates_service.py
airalo/services/future_order_service.py
airalo/services/installation_instructions_service.py
airalo/services/oauth_service.py
airalo/services/order_service.py
airalo/services/packages_service.py
airalo/services/sim_service.py
airalo/services/topup_service.py
airalo/services/voucher_service.py
airalo_sdk-1.0.0.dist-info/licenses/LICENSE
airalo_sdk-1.0.0.dist-info/METADATA
airalo_sdk-1.0.0.dist-info/WHEEL
airalo_sdk-1.0.0.dist-info/top_level.txt
airalo_sdk-1.0.0.dist-info/RECORD
