Metadata-Version: 2.4
Name: airalo-sdk
Version: 1.0.0
Summary: Official Airalo Python SDK for Airalo's REST API
Home-page: https://github.com/Airalo/airalo-python-sdk
Author: Airalo
Author-email: Airalo <partner.integration@airalo.com>
License: MIT License
Classifier: Programming Language :: Python :: 3
Classifier: License :: OSI Approved :: MIT License
Requires-Python: >=3.1
License-File: LICENSE
Requires-Dist: requests
Requires-Dist: cryptography
Dynamic: author
Dynamic: home-page
Dynamic: license-file
Dynamic: requires-python
